paspale/__init__.py
paspale/base.py
paspale/cli.py
paspale/colors.py
paspale/config.py
paspale/paspale.py
paspale/py.typed
paspale/plotters/__init__.py
paspale/plotters/bar.py
paspale/plotters/dual_axis.py
paspale/plotters/kde.py
paspale/plotters/line.py
paspale/plotters/stacked.py
paspale-0.1.0.dist-info/licenses/LICENSE
paspale-0.1.0.dist-info/METADATA
paspale-0.1.0.dist-info/WHEEL
paspale-0.1.0.dist-info/entry_points.txt
paspale-0.1.0.dist-info/top_level.txt
paspale-0.1.0.dist-info/RECORD
